unitree_sdk2-1.0.1.dist-info/licenses/LICENSE
unitree_sdk2py/__init__.py
unitree_sdk2py/core/__init__.py
unitree_sdk2py/core/channel.py
unitree_sdk2py/core/channel_config.py
unitree_sdk2py/core/channel_name.py
unitree_sdk2py/go2/__init__.py
unitree_sdk2py/go2/obstacles_avoid/__init__.py
unitree_sdk2py/go2/obstacles_avoid/obstacles_avoid_api.py
unitree_sdk2py/go2/obstacles_avoid/obstacles_avoid_client.py
unitree_sdk2py/go2/robot_state/__init__.py
unitree_sdk2py/go2/robot_state/robot_state_api.py
unitree_sdk2py/go2/robot_state/robot_state_client.py
unitree_sdk2py/go2/sport/__init__.py
unitree_sdk2py/go2/sport/sport_api.py
unitree_sdk2py/go2/sport/sport_client.py
unitree_sdk2py/go2/video/__init__.py
unitree_sdk2py/go2/video/video_api.py
unitree_sdk2py/go2/video/video_client.py
unitree_sdk2py/go2/vui/__init__.py
unitree_sdk2py/go2/vui/vui_api.py
unitree_sdk2py/go2/vui/vui_client.py
unitree_sdk2py/idl/__init__.py
unitree_sdk2py/idl/default.py
unitree_sdk2py/idl/builtin_interfaces/__init__.py
unitree_sdk2py/idl/builtin_interfaces/msg/__init__.py
unitree_sdk2py/idl/builtin_interfaces/msg/dds_/_Time_.py
unitree_sdk2py/idl/builtin_interfaces/msg/dds_/__init__.py
unitree_sdk2py/idl/geometry_msgs/__init__.py
unitree_sdk2py/idl/geometry_msgs/msg/__init__.py
unitree_sdk2py/idl/geometry_msgs/msg/dds_/_Point32_.py
unitree_sdk2py/idl/geometry_msgs/msg/dds_/_PointStamped_.py
unitree_sdk2py/idl/geometry_msgs/msg/dds_/_Point_.py
unitree_sdk2py/idl/geometry_msgs/msg/dds_/_Pose2D_.py
unitree_sdk2py/idl/geometry_msgs/msg/dds_/_PoseStamped_.py
unitree_sdk2py/idl/geometry_msgs/msg/dds_/_PoseWithCovarianceStamped_.py
unitree_sdk2py/idl/geometry_msgs/msg/dds_/_PoseWithCovariance_.py
unitree_sdk2py/idl/geometry_msgs/msg/dds_/_Pose_.py
unitree_sdk2py/idl/geometry_msgs/msg/dds_/_QuaternionStamped_.py
unitree_sdk2py/idl/geometry_msgs/msg/dds_/_Quaternion_.py
unitree_sdk2py/idl/geometry_msgs/msg/dds_/_TwistStamped_.py
unitree_sdk2py/idl/geometry_msgs/msg/dds_/_TwistWithCovarianceStamped_.py
unitree_sdk2-1.0.1.dist-info/METADATA
unitree_sdk2-1.0.1.dist-info/WHEEL
unitree_sdk2-1.0.1.dist-info/top_level.txt
unitree_sdk2-1.0.1.dist-info/RECORD
