Metadata-Version: 2.4
Name: unitree_sdk2
Version: 1.0.1
Summary: Unitree robot sdk version 2 for python
Author: UnitreeRobotics
Author-email: unitree@unitree.com
License: BSD-3-Clause
Project-URL: Source Code, https://github.com/unitreerobotics/unitree_sdk2_python
Requires-Python: >=3.8
License-File: LICENSE
Requires-Dist: cyclonedds==0.10.2
Requires-Dist: numpy
Requires-Dist: opencv-python
Dynamic: author
Dynamic: author-email
Dynamic: description
Dynamic: description-content-type
Dynamic: license
Dynamic: license-file
Dynamic: project-url
Dynamic: requires-dist
Dynamic: requires-python
Dynamic: summary
